docs/source/conf.py
examples/example.py
isadora/__init__.py
isadora/base.py
isadora/cli.py
isadora/constants.py
isadora/units.py
isadora-1.1.500.dist-info/licenses/LICENSE
tests/conftest.py
tests/test_ardc_reference.py
tests/test_derived_quantities.py
tests/test_physical_consistency.py
tests/test_reference_atmospheres.py
tests/test_units_and_invariance.py
isadora-1.1.500.dist-info/METADATA
isadora-1.1.500.dist-info/WHEEL
isadora-1.1.500.dist-info/top_level.txt
isadora-1.1.500.dist-info/RECORD
