Metadata-Version: 2.4
Name: isadora
Version: 1.1.500
Summary: An ICAO-compliant Implementation of the International Standard Atmosphere.
Author-email: Kolawole Andrew <andrewolakola@gmail.com>
License: MIT
Project-URL: Homepage, https://github.com/techkaduna/isadora
Project-URL: Repository, https://github.com/techkaduna/isadora
Keywords: units,physics,aerospace,atmosphere,meterology,engineering,unit-conversion,unit-aware computing
Classifier: Development Status :: 4 - Beta
Classifier: Intended Audience :: Science/Research
Classifier: Intended Audience :: Developers
Classifier: Intended Audience :: Education
Classifier: License :: OSI Approved :: MIT License
Classifier: Programming Language :: Python :: 3
Classifier: Topic :: Scientific/Engineering
Classifier: Topic :: Scientific/Engineering :: Physics
Classifier: Operating System :: OS Independent
Requires-Python: >=3.12
License-File: LICENSE
Requires-Dist: mudu>=1.1.500
Dynamic: license-file
